agent_mcp_server/__init__.py
agent_mcp_server/create.py
agent_mcp_server/mcp-server.json
agent_mcp_server/mcp_logging.py
agent_mcp_server/mcp_server_config.py
agent_mcp_server/template/Dockerfile.template
agent_mcp_server/template/__init__.py
agent_mcp_server/template/main.py.template
agent_mcp_server/template/requirements.txt
agent_mcp_server/template/server.py.template
agent_mcp_server/template/service.py.template
agent_mcp_server-0.0.4.0.dist-info/METADATA
agent_mcp_server-0.0.4.0.dist-info/WHEEL
agent_mcp_server-0.0.4.0.dist-info/top_level.txt
agent_mcp_server-0.0.4.0.dist-info/RECORD
