Metadata-Version: 2.4
Name: agent-mcp-server
Version: 0.0.4.0
Summary: Agent MCP服务框架
Home-page: https://codeup.aliyun.com/64650c96168f0a5963451dec/lib/fast-model-server/blob/master/README.md
Author: fb_linux
Author-email: fb_linux@163.com
License: MIT
Classifier: Programming Language :: Python
Classifier: Programming Language :: Python :: 3
Classifier: Programming Language :: Python :: 3.10
Requires-Dist: fastmcp==2.14.1
Requires-Dist: uv==0.9.18
Requires-Dist: redis
